odoo/addons/l10n_ar_afipws/README.rst
odoo/addons/l10n_ar_afipws/__init__.py
odoo/addons/l10n_ar_afipws/__manifest__.py
odoo/addons/l10n_ar_afipws/i18n/es_AR.po
odoo/addons/l10n_ar_afipws/i18n/l10n_ar_afipws.pot
odoo/addons/l10n_ar_afipws/models/__init__.py
odoo/addons/l10n_ar_afipws/models/afipws_certificate.py
odoo/addons/l10n_ar_afipws/models/afipws_certificate_alias.py
odoo/addons/l10n_ar_afipws/models/afipws_connection.py
odoo/addons/l10n_ar_afipws/models/res_company.py
odoo/addons/l10n_ar_afipws/models/res_config_settings.py
odoo/addons/l10n_ar_afipws/readme/CONTRIBUTORS.rst
odoo/addons/l10n_ar_afipws/readme/DESCRIPTION.rst
odoo/addons/l10n_ar_afipws/readme/HISTORY.rst
odoo/addons/l10n_ar_afipws/readme/ROADMAP.rst
odoo/addons/l10n_ar_afipws/readme/USAGE.rst
odoo/addons/l10n_ar_afipws/security/ir.model.access.csv
odoo/addons/l10n_ar_afipws/security/security.xml
odoo/addons/l10n_ar_afipws/security/security.xml.save
odoo/addons/l10n_ar_afipws/static/description/icon.png
odoo/addons/l10n_ar_afipws/static/description/index.html
odoo/addons/l10n_ar_afipws/views/afipws_certificate_alias_view.xml
odoo/addons/l10n_ar_afipws/views/afipws_certificate_view.xml
odoo/addons/l10n_ar_afipws/views/afipws_connection_view.xml
odoo/addons/l10n_ar_afipws/views/afipws_menuitem.xml
odoo/addons/l10n_ar_afipws/views/res_config_settings.xml
odoo/addons/l10n_ar_afipws/wizard/__init__.py
odoo/addons/l10n_ar_afipws/wizard/upload_certificate_view.xml
odoo/addons/l10n_ar_afipws/wizard/upload_certificate_wizard.py
odoo_addon_l10n_ar_afipws-16.0.1.0.0.6.dist-info/METADATA
odoo_addon_l10n_ar_afipws-16.0.1.0.0.6.dist-info/WHEEL
odoo_addon_l10n_ar_afipws-16.0.1.0.0.6.dist-info/top_level.txt
odoo_addon_l10n_ar_afipws-16.0.1.0.0.6.dist-info/RECORD
