Metadata-Version: 2.1
Name: odoo-addon-l10n-ar-afipws
Version: 16.0.1.0.0.6
Summary: Integration for Argentina Electronic invoice webservices
Home-page: https://github.com/OCA/l10n-argentina
Author: Nimarosa, ADHOC SA, Moldeo Interactive, Exemax, Codize, Odoo Community Association (OCA)
Author-email: support@odoo-community.org
License: AGPL-3
Platform: UNKNOWN
Classifier: Programming Language :: Python
Classifier: Framework :: Odoo
Classifier: Framework :: Odoo :: 16.0
Classifier: License :: OSI Approved :: GNU Affero General Public License v3
Requires-Python: >=3.10
Requires-Dist: future
Requires-Dist: odoo <16.1dev,>=16.0a
Requires-Dist: pyOpenSSL
Requires-Dist: pysimplesoap
